{"md5":"5ba0fea5190d8cb673b74caf762b3522","headers":{"title":"Sonic Cannon[GENIUS]","artist":"犬 obj.O","genre":"ハイギア","playlevel":"25","base_bpm":260.0},"mode":"SP","scope":"playable_only","scaling_mode":"p99_linear","params":{"stream_window_ticks":48,"stream_density_threshold_per_beat":4.0,"peak_window_ticks":192,"peak_min_window_notes":4,"peak_min_window_sec":0.05,"felt_bpm_trigger_eff_bpm":500.0,"felt_bpm_trigger_peak_per_sec":200.0,"felt_bpm_target_peak_per_sec":100.0,"felt_bpm_floor":30.0,"jack_window_ticks":24,"soft_burst_ref":8.0,"soft_freq_ref":0.1,"soft_burst_exp":1.5,"soft_freq_exp":1.5,"chord_time_threshold_ms":16.67,"sp_distraction_min_scratches":3,"dp_distraction_window_sec_min":0.2,"dp_distraction_window_sec_max":0.8,"stream_density_ref_per_sec":40.0,"peak_density_ref_per_sec":70.0,"chord_size_ref":3.5,"ln_simultaneity_ref":0.05,"scratch_density_ref_per_sec":1.5,"scratch_ratio_ref":0.1,"distraction_density_ref":2.0,"distraction_event_ref":0.15},"raw_axes":{"chord":2.0819912152269398,"stream":34.05080868959546,"scratch":0.09428982251317186,"soft":0.0,"ln":0.0045207956600361665,"stair":0.22124542124542124,"peak":55.25,"distraction":1.627570621468926,"pure_jack_raw":0.0,"flow_break_raw":0.030498533724340162},"x_chord":0.524,"x_stream":0.849,"x_scratch":0.225,"x_soft":0.0,"x_ln":0.072,"x_stair":0.652,"x_peak":0.891,"x_distraction":0.43,"jack_signal":0.029,"noise_budget":0.756,"submetrics":{"chord":{"chord_rate":0.6530014641288433,"avg_chord_size":3.188340807174888,"chord_positions":892,"total_positions":1366},"stream":{"stream_coverage":0.9900542495479204,"stream_density_mean":7.93681652490887,"stream_density_mean_per_sec":34.39287160793843,"stream_windows":17,"notes_in_stream":3285,"total_notes":3318,"intervals":[[156,1008],[1020,1560],[1716,3096],[3228,4848],[5148,5880],[5928,8400],[8412,8592],[8604,8784],[8796,9168],[9180,9360],[9372,9552],[9564,11352],[12636,12720],[12828,13680],[13980,15384],[15516,16932],[17052,23280]]},"scratch":{"scratch_ratio":0.05726341169379144,"scratch_positions_ratio":0.1390922401171303,"scratch_with_key_chord_rate":0.8631578947368421,"scratch_per_sec":1.6465980584142328,"scratch_burst_max_per_sec":12.0,"scratch_burst_window_sec":1.0,"scratch_notes":190,"scratch_positions":190,"total_notes":3318,"total_positions":1366,"chart_seconds":115.38942307692308},"soft":{"base_bpm":260.0,"intensity":0.0,"up_intensity":0.0,"down_intensity":0.0,"max_intensity":0.0,"max_up_intensity":0.0,"max_down_intensity":0.0,"step_frequency":0.0,"ramp_frequency":0.0,"continuity_beats":0.0,"off_base_note_ratio":0.0,"gimmick_burst_score":0.0,"max_off_base_density_per_beat":0.0,"base_mean_density_per_beat":6.634,"base_density_source":"on_base","distinct_off_base_bpm_count":0,"bpm_change_events":0,"measure_count":126},"ln":{"ln_ratio":0.003315250150693189,"ln_hold_time_mean_beats":1.6193181818181819,"ln_simultaneity_rate":0.0015069318866787222,"ln_simultaneity_weighted":0.0045207956600361665,"ln_count":11,"ln_positions":4,"total_notes":3318},"stair":{"stair_index":0.22124542124542124,"stair_transitions":302,"eligible_transitions":1365},"peak":{"peak_local_max_density":12.75,"peak_local_max_density_per_sec":55.25,"peak_max_chord_size":7,"peak_concentration":0.298372513562387,"total_notes":3318,"intervals":[[3648,4824],[7392,8220],[9780,10608],[18288,18684],[20100,20352],[20568,21024],[22128,22500],[22608,22956],[22980,23280]]},"jack":{"jack_pairs":3,"jack_in_stream_pairs":3,"jack_outside_pairs":0,"pure_jack_per_sec":0.0,"flow_break_per_stream_sec":0.030498533724340162,"stream_seconds":98.36538461538466,"non_stream_seconds":17.024038461538424,"chart_seconds":115.38942307692308,"window_ticks":24,"min_region_sec":10.0},"distraction":{"mode_formulation":"SP","qualifying_window_count":9,"qualifying_scratches":157,"qualifying_flow_sec":85.09615384615387,"distract_density":1.8449717514124289,"distract_event_per_sec":0.10576271186440675,"scratch_chord_pair_count":247,"chord_time_threshold_sec":0.01667,"min_scratches":3}},"warnings":["Unterminated LNOBJ LN on lane P1_KEY1 started at m121 pos0.0; closing at EOF","Unterminated LNOBJ LN on lane P1_KEY4 started at m121 pos0.0; closing at EOF","Unterminated LNOBJ LN on lane P1_KEY6 started at m121 pos0.0; closing at EOF","Unterminated LNOBJ LN on lane P1_KEY2 started at m121 pos0.0; closing at EOF","Unterminated LNOBJ LN on lane P1_SCR started at m125 pos0.0; closing at EOF","Unterminated LNOBJ LN on lane P1_KEY3 started at m121 pos0.0; closing at EOF","Unterminated LNOBJ LN on lane P1_KEY7 started at m120 pos0.9375; closing at EOF","Unterminated LNOBJ LN on lane P1_KEY5 started at m121 pos0.0; closing at EOF"],"tags":["stream_heavy","scratch_active","stair_focused","peak_intense","distraction_heavy","scratch_burst","scratch_chord","peak_outlier","dense_chart","fast_chart","pure_stream"],"scales":["st"]}