{"md5":"4736cfba80aead33107abad1cdf0c3f0","headers":{"title":"チョウの標本 [...]","artist":"Process 2.3.1. / obj.go2","genre":"","playlevel":"25","base_bpm":170.0},"mode":"SP","scope":"playable_only","scaling_mode":"reference","params":{"stream_window_ticks":48,"stream_density_threshold_per_beat":4.0,"peak_window_ticks":192,"jack_window_ticks":24,"soft_burst_ref":8.0,"soft_freq_ref":0.1,"soft_burst_exp":1.5,"soft_freq_exp":1.5,"stream_density_ref_per_sec":40.0,"peak_density_ref_per_sec":70.0,"chord_size_ref":3.5,"ln_simultaneity_ref":0.05},"x_chord":0.43194429333043194,"x_stream":0.8322801316000641,"x_scratch":0.026565464895635674,"x_soft":6.56046228398736e-05,"x_ln":0.0,"x_stair":0.11432926829268293,"x_peak":0.7892857142857143,"x_jack":0.0007621951219512195,"submetrics":{"chord":{"chord_rate":0.504950495049505,"avg_chord_size":2.9939668174962293,"chord_positions":663,"total_positions":1313},"stream":{"stream_coverage":0.9867172675521821,"stream_density_mean":11.917336394948336,"stream_density_mean_per_sec":33.73935610409491,"stream_windows":5,"notes_in_stream":2600,"total_notes":2635},"scratch":{"scratch_ratio":0.026565464895635674,"scratch_positions_ratio":0.053313023610053314,"scratch_with_key_chord_rate":0.9285714285714286,"scratch_notes":70,"scratch_positions":70,"total_notes":2635,"total_positions":1313},"soft":{"base_bpm":170.0,"intensity":0.0017836812144212523,"up_intensity":0.0004554079696394687,"down_intensity":0.0013282732447817836,"max_intensity":0.6,"max_up_intensity":0.6,"max_down_intensity":0.5,"step_frequency":0.052083333333333336,"ramp_frequency":0.052083333333333336,"continuity_beats":57.604166666666664,"off_base_note_ratio":0.003415559772296015,"gimmick_burst_score":0.024985085756681253,"max_off_base_density_per_beat":0.25,"base_mean_density_per_beat":8.101851851851851,"base_density_source":"on_base","distinct_off_base_bpm_count":2,"bpm_change_events":5,"measure_count":96},"ln":{"ln_ratio":0.0,"ln_hold_time_mean_beats":0.0,"ln_simultaneity_rate":0.0,"ln_simultaneity_weighted":0.0,"ln_count":0,"ln_positions":0,"total_notes":2635},"stair":{"stair_index":0.11432926829268293,"stair_transitions":150,"eligible_transitions":1312},"peak":{"peak_local_max_density":19.5,"peak_local_max_density_per_sec":55.25,"peak_max_chord_size":5,"peak_concentration":0.5495256166982923,"total_notes":2635},"jack":{"jack_ratio":0.0007621951219512195,"jack_transitions":1,"all_transitions":1312}},"warnings":[],"tags":["stream_heavy","burst_focused","pure_stream"],"scales":["st"]}