{"md5":"bf9396b2d6cf5673654543828de0e126","headers":{"title":"Jack-the-Ripper◆[7EXPERT]","artist":"sasakure.UK","genre":"progressive","playlevel":"11","base_bpm":210.0},"mode":"SP","scope":"playable_only","scaling_mode":"p99_linear","params":{"stream_window_ticks":48,"stream_density_threshold_per_beat":4.0,"peak_window_ticks":192,"peak_min_window_notes":4,"peak_min_window_sec":0.05,"felt_bpm_trigger_eff_bpm":500.0,"felt_bpm_trigger_peak_per_sec":200.0,"felt_bpm_target_peak_per_sec":100.0,"felt_bpm_floor":30.0,"jack_window_ticks":24,"soft_burst_ref":8.0,"soft_freq_ref":0.1,"soft_burst_exp":1.5,"soft_freq_exp":1.5,"chord_time_threshold_ms":16.67,"sp_distraction_min_scratches":3,"sp_distraction_bin_sec":0.25,"sp_distraction_t_key":2,"sp_distraction_gap_bins":2,"dp_distraction_window_sec_min":0.2,"dp_distraction_window_sec_max":0.8,"stream_density_ref_per_sec":40.0,"peak_density_ref_per_sec":70.0,"chord_size_ref":3.5,"ln_simultaneity_ref":0.05,"scratch_density_ref_per_sec":1.5,"scratch_ratio_ref":0.1,"distraction_density_ref":2.0,"distraction_event_ref":0.15},"raw_axes":{"chord":0.7215189873417722,"stream":5.215613273921201,"scratch_per_sec":0.8980302753815297,"scratch_burst_max_per_sec":8.0,"scratch_max_run_sec":9.640350877192986,"soft":0.07292943985545854,"stair":0.06521739130434782,"peak":18.0,"ln_m1_short_rate_rt":0.0,"ln_m2_density_rt":14.455834476170118,"ln_m2_burst_max_rt":58.0,"ln_m3_density_rt":14.455834476170118,"ln_m_concurrent_rt":0.22993506825502336,"adv_hand_imb":0.6172839506172839,"adv_rel_pressure_1beat":0.7283950617283951,"adv_ln_hold_min_beats":0.4140625,"adv_ln_chord_big_rate":0.04081632653061224,"adv_ln_scatter_cv":2.5737011022836294,"distraction":1.4778608468877141},"x_chord":0.185,"x_stream":0.135,"x_scratch":0.239,"x_soft":0.219,"x_ln":0.784,"x_stair":0.185,"x_peak":0.302,"x_distraction":0.091,"ln_advanced_score":0.763,"submetrics":{"chord":{"chord_rate":0.31518987341772153,"avg_chord_size":2.289156626506024,"chord_positions":249,"total_positions":790},"stream":{"stream_coverage":0.35365853658536583,"stream_density_mean":4.528846153846154,"stream_density_mean_per_sec":14.747596153846153,"stream_windows":42,"notes_in_stream":348,"total_notes":984,"intervals":[[2388,2448],[2460,2520],[2532,2640],[3276,3360],[4284,4368],[4584,4668],[4680,4740],[4752,4812],[4824,4884],[8568,9120],[9144,9204],[9216,9276],[9288,9348],[9360,9420],[9432,9492],[9504,9564],[9576,9636],[9660,9708],[9756,9804],[10140,10188],[11100,11148],[11196,11244],[12492,12576],[12612,12696],[12732,12780],[16392,16692],[19344,19416],[19776,19824],[19908,20016],[20496,20568],[20928,20976],[21060,21168],[21288,21972],[21984,22044],[22056,22164],[22800,22884],[23124,23184],[23196,23256],[23268,23328],[23340,23400],[23412,23472],[23484,23676]]},"scratch":{"scratch_ratio":0.11431143114311432,"scratch_positions_ratio":0.16075949367088607,"scratch_with_key_chord_rate":0.5826771653543307,"scratch_per_sec":0.8980302753815297,"scratch_burst_max_per_sec":8.0,"scratch_burst_window_sec":1.0,"scratch_max_run_sec":9.640350877192986,"ls_count":3,"ls_per_sec":0.021213313591689677,"ls_complexity_mean":0,"scratch_notes":127,"scratch_positions":127,"total_notes":1111,"total_positions":790,"chart_seconds":141.42062186716794},"soft":{"base_bpm":240.0,"intensity":0.09155040504050405,"up_intensity":0.0,"down_intensity":0.09155040504050405,"max_intensity":0.78125,"max_up_intensity":0.0,"max_down_intensity":0.78125,"step_frequency":0.0625,"ramp_frequency":0.046875,"continuity_beats":303.625,"off_base_note_ratio":0.5877587758775877,"gimmick_burst_score":1.1668710376873366,"max_off_base_density_per_beat":13.538461538461538,"base_mean_density_per_beat":2.21256038647343,"base_density_source":"on_base","distinct_off_base_bpm_count":4,"bpm_change_events":19,"measure_count":128},"ln":{"ln_ratio":0.14581458145814583,"ln_hold_time_mean_beats":1.0441100823045268,"ln_simultaneity_rate":0.09000900090009001,"ln_simultaneity_weighted":0.09180918091809182,"ln_count":162,"ln_count_raw":162,"ln_positions":147,"total_notes":1111,"m1_short_count_rt":0,"m1_short_rate_rt":0.0,"m2_long_count_rt":162,"m2_density_rt":14.455834476170118,"m2_burst_max_rt":58.0,"m3_density_rt":14.455834476170118,"m_concurrent_rt":0.22993506825502336,"total_long_sec":51.81298950501249,"long_active_sec":42.126605576441065,"long_hold_sec_mean":0.3198332685494598,"long_hold_sec_max":0.8080357142857224,"adv_hand_imb":0.6172839506172839,"adv_rel_pressure_1beat":0.7283950617283951,"adv_ln_hold_min_beats":0.4140625,"adv_ln_chord_big_rate":0.04081632653061224,"adv_ln_scatter_cv":2.5737011022836294},"stair":{"stair_index":0.06521739130434782,"stair_transitions":48,"eligible_transitions":736},"peak":{"peak_local_max_density":7.0,"peak_local_max_density_per_sec":18.0,"peak_max_chord_size":3,"peak_concentration":0.3150406504065041,"total_notes":984,"intervals":[[2412,2760],[4512,4980],[8544,9204],[16368,16764],[19344,19560],[19776,20160],[20496,20712],[20928,22284],[23400,23784]]},"jack":{"jack_pairs":2,"jack_in_stream_pairs":2,"jack_outside_pairs":0,"pure_jack_per_sec":0.0,"flow_break_per_stream_sec":0.07121284374503258,"stream_seconds":28.08482142857143,"non_stream_seconds":113.33580043859651,"chart_seconds":141.42062186716794,"window_ticks":24,"min_region_sec":10.0},"distraction":{"mode_formulation":"SP","v3_score":1.4778608468877141,"qualifying_intervals":5,"qualifying_flow_sec":88.0,"qualifying_scratches":88,"scratch_chord_pair_count":63,"chord_time_threshold_sec":0.01667,"min_scratches":3,"bin_sec":0.25,"t_key":2,"gap_bins":2}},"warnings":["Line has odd-length data, truncating: '#00106:02030405060708090A0B0C0D0E0F101112131415161718191A1B1C1D1E1F202102030405060708090A0B0C0D0E0F101112131415161718191A1B1C1D1E1F202'","Line has odd-length data, truncating: '#00206:02030405060708090A0B0C0D0E0F101112131415161718191A1B1C1D1E1F202102030405060708090A0B0C0D0E0F101112131415161718191A1B1C1D1E1F202'","Line has odd-length data, truncating: '#00306:02030405060708090A0B0C0D0E0F101112131415161718191A1B1C1D1E1F202102030405060708090A0B0C0D0E0F101112131415161718191A1B1C1D1E1F202'","Line has odd-length data, truncating: '#00406:02030405060708090A0B0C0D0E0F101112131415161718191A1B1C1D1E1F202102030405060708090A0B0C0D0E0F101112131415161718191A1B1C1D1E1F202'","Line has odd-length data, truncating: '#00506:02030405060708090A0B0C0D0E0F101112131415161718191A1B1C1D1E1F202102030405060708090A0B0C0D0E0F101112131415161718191A1B1C1D1E1F202'","Line has odd-length data, truncating: '#00606:02030405060708090A0B0C0D0E0F101112131415161718191A1B1C1D1E1F202102030405060708090A0B0C0D0E0F101112131415161718191A1B1C1D1E1F202'","Line has odd-length data, truncating: '#00706:02030405060708090A0B0C0D0E0F101112131415161718191A1B1C1D1E1F202102030405060708090A0B0C0D0E0F101112131415161718191A1B1C1D1E1F202'","Line has odd-length data, truncating: '#00806:02030405060708090A0B0C0D0E0F101112131415161718191A1B1C1D1E1F202102030405060708090A0B0C0D0E0F101112131415161718191A1B1C1D1E1F202'","Line has odd-length data, truncating: '#00906:02030405060708090A0B0C0D0E0F101112131415161718191A1B1C1D1E1F202102030405060708090A0B0C0D0E0F101112131415161718191A1B1C1D1E1F202'","Line has odd-length data, truncating: '#01006:02030405060708090A0B0C0D0E0F101112131415161718191A1B1C1D1E1F202102030405060708090A0B0C0D0E0F101112131415161718191A1B1C1D1E1F202'","Line has odd-length data, truncating: '#01106:02030405060708090A0B0C0D0E0F101112131415161718191A1B1C1D1E1F202102030405060708090A0B0C0D0E0F101112131415161718191A1B1C1D1E1F202'","Line has odd-length data, truncating: '#01206:02030405060708090A0B0C0D0E0F101112131415161718191A1B1C1D1E1F202102030405060708090A0B0C0D0E0F101112131415161718191A1B1C1D1E1F202'","Line has odd-length data, truncating: '#01306:02030405060708090A0B0C0D0E0F101112131415161718191A1B1C1D1E1F202102030405060708090A0B0C0D0E0F101112131415161718191A1B1C1D1E1F202'","Line has odd-length data, truncating: '#01406:02030405060708090A0B0C0D0E0F101112131415161718191A1B1C1D1E1F202102030405060708090A0B0C0D0E0F101112131415161718191A1B1C1D1E1F202'","Line has odd-length data, truncating: '#01506:02030405060708090A0B0C0D0E0F101112131415161718191A1B1C1D1E1F202102030405060708090A0B0C0D0E0F101112131415161718191A1B1C1D1E1F202'","Line has odd-length data, truncating: '#01606:02030405060708090A0B0C0D0E0F101112131415161718191A1B1C1D1E1F202102030405060708090A0B0C0D0E0F101112131415161718191A1B1C1D1E1F202'","Line has odd-length data, truncating: '#01706:02030405060708090A0B0C0D0E0F101112131415161718191A1B1C1D1E1F202102030405060708090A0B0C0D0E0F101112131415161718191A1B1C1D1E1F202'","Line has odd-length data, truncating: '#01806:02030405060708090A0B0C0D0E0F101112131415161718191A1B1C1D1E1F202102030405060708090A0B0C0D0E0F101112131415161718191A1B1C1D1E1F202'","Line has odd-length data, truncating: '#01906:02030405060708090A0B0C0D0E0F101112131415161718191A1B1C1D1E1F202102030405060708090A0B0C0D0E0F101112131415161718191A1B1C1D1E1F202'","Line has odd-length data, truncating: '#02006:02030405060708090A0B0C0D0E0F101112131415161718191A1B1C1D1E1F202102030405060708090A0B0C0D0E0F101112131415161718191A1B1C1D1E1F202'","Line has odd-length data, truncating: '#02106:02030405060708090A0B0C0D0E0F101112131415161718191A1B1C1D1E1F202102030405060708090A0B0C0D0E0F101112131415161718191A1B1C1D1E1F202'","Line has odd-length data, truncating: '#02206:02030405060708090A0B0C0D0E0F101112131415161718191A1B1C1D1E1F202102030405060708090A0B0C0D0E0F101112131415161718191A1B1C1D1E1F202'","Line has odd-length data, truncating: '#02306:02030405060708090A0B0C0D0E0F101112131415161718191A1B1C1D1E1F202102030405060708090A0B0C0D0E0F101112131415161718191A1B1C1D1E1F202'","Line has odd-length data, truncating: '#02406:02030405060708090A0B0C0D0E0F101112131415161718191A1B1C1D1E1F202102030405060708090A0B0C0D0E0F101112131415161718191A1B1C1D1E1F202'","Line has odd-length data, truncating: '#02506:02030405060708090A0B0C0D0E0F101112131415161718191A1B1C1D1E1F202102030405060708090A0B0C0D0E0F101112131415161718191A1B1C1D1E1F202'","Line has odd-length data, truncating: '#02606:02030405060708090A0B0C0D0E0F101112131415161718191A1B1C1D1E1F202102030405060708090A0B0C0D0E0F101112131415161718191A1B1C1D1E1F202'","Line has odd-length data, truncating: '#02706:02030405060708090A0B0C0D0E0F101112131415161718191A1B1C1D1E1F202102030405060708090A0B0C0D0E0F101112131415161718191A1B1C1D1E1F202'","Line has odd-length data, truncating: '#02806:02030405060708090A0B0C0D0E0F101112131415161718191A1B1C1D1E1F202102030405060708090A0B0C0D0E0F101112131415161718191A1B1C1D1E1F202'","Line has odd-length data, truncating: '#02906:02030405060708090A0B0C0D0E0F101112131415161718191A1B1C1D1E1F202102030405060708090A0B0C0D0E0F101112131415161718191A1B1C1D1E1F202'","Line has odd-length data, truncating: '#03006:02030405060708090A0B0C0D0E0F101112131415161718191A1B1C1D1E1F202102030405060708090A0B0C0D0E0F101112131415161718191A1B1C1D1E1F202'","Line has odd-length data, truncating: '#03106:02030405060708090A0B0C0D0E0F101112131415161718191A1B1C1D1E1F202102030405060708090A0B0C0D0E0F101112131415161718191A1B1C1D1E1F202'","Line has odd-length data, truncating: '#03206:02030405060708090A0B0C0D0E0F101112131415161718191A1B1C1D1E1F202102030405060708090A0B0C0D0E0F101112131415161718191A1B1C1D1E1F202'","Line has odd-length data, truncating: '#03306:02030405060708090A0B0C0D0E0F101112131415161718191A1B1C1D1E1F202102030405060708090A0B0C0D0E0F101112131415161718191A1B1C1D1E1F202'","Line has odd-length data, truncating: '#03406:02030405060708090A0B0C0D0E0F101112131415161718191A1B1C1D1E1F202102030405060708090A0B0C0D0E0F101112131415161718191A1B1C1D1E1F202'","Line has odd-length data, truncating: '#03506:02030405060708090A0B0C0D0E0F101112131415161718191A1B1C1D1E1F202102030405060708090A0B0C0D0E0F101112131415161718191A1B1C1D1E1F202'","Line has odd-length data, truncating: '#03606:02030405060708090A0B0C0D0E0F101112131415161718191A1B1C1D1E1F202102030405060708090A0B0C0D0E0F101112131415161718191A1B1C1D1E1F202'","Line has odd-length data, truncating: '#03706:02030405060708090A0B0C0D0E0F101112131415161718191A1B1C1D1E1F202102030405060708090A0B0C0D0E0F101112131415161718191A1B1C1D1E1F202'","Line has odd-length data, truncating: '#03806:02030405060708090A0B0C0D0E0F101112131415161718191A1B1C1D1E1F202102030405060708090A0B0C0D0E0F101112131415161718191A1B1C1D1E1F202'","Line has odd-length data, truncating: '#03906:02030405060708090A0B0C0D0E0F101112131415161718191A1B1C1D1E1F202102030405060708090A0B0C0D0E0F101112131415161718191A1B1C1D1E1F202'","Line has odd-length data, truncating: '#04006:02030405060708090A0B0C0D0E0F101112131415161718191A1B1C1D1E1F202102030405060708090A0B0C0D0E0F101112131415161718191A1B1C1D1E1F202'","Line has odd-length data, truncating: '#04106:02030405060708090A0B0C0D0E0F101112131415161718191A1B1C1D1E1F202102030405060708090A0B0C0D0E0F101112131415161718191A1B1C1D1E1F202'","Line has odd-length data, truncating: '#04206:02030405060708090A0B0C0D0E0F101112131415161718191A1B1C1D1E1F202102030405060708090A0B0C0D0E0F101112131415161718191A1B1C1D1E1F202'","Line has odd-length data, truncating: '#04306:02030405060708090A0B0C0D0E0F101112131415161718191A1B1C1D1E1F202102030405060708090A0B0C0D0E0F101112131415161718191A1B1C1D1E1F202'","Line has odd-length data, truncating: '#04406:02030405060708090A0B0C0D0E0F101112131415161718191A1B1C1D1E1F202102030405060708090A0B0C0D0E0F101112131415161718191A1B1C1D1E1F202'","Line has odd-length data, truncating: '#04506:02030405060708090A0B0C0D0E0F101112131415161718191A1B1C1D1E1F202102030405060708090A0B0C0D0E0F101112131415161718191A1B1C1D1E1F202'","Line has odd-length data, truncating: '#04606:02030405060708090A0B0C0D0E0F101112131415161718191A1B1C1D1E1F202102030405060708090A0B0C0D0E0F101112131415161718191A1B1C1D1E1F202'","Line has odd-length data, truncating: '#04706:02030405060708090A0B0C0D0E0F101112131415161718191A1B1C1D1E1F202102030405060708090A0B0C0D0E0F101112131415161718191A1B1C1D1E1F202'","Line has odd-length data, truncating: '#04806:02030405060708090A0B0C0D0E0F101112131415161718191A1B1C1D1E1F202102030405060708090A0B0C0D0E0F101112131415161718191A1B1C1D1E1F202'","Line has odd-length data, truncating: '#04906:02030405060708090A0B0C0D0E0F101112131415161718191A1B1C1D1E1F202102030405060708090A0B0C0D0E0F101112131415161718191A1B1C1D1E1F202'","Line has odd-length data, truncating: '#05006:02030405060708090A0B0C0D0E0F101112131415161718191A1B1C1D1E1F202102030405060708090A0B0C0D0E0F101112131415161718191A1B1C1D1E1F202'","Line has odd-length data, truncating: '#05106:02030405060708090A0B0C0D0E0F101112131415161718191A1B1C1D1E1F202102030405060708090A0B0C0D0E0F101112131415161718191A1B1C1D1E1F202'","Line has odd-length data, truncating: '#05206:02030405060708090A0B0C0D0E0F101112131415161718191A1B1C1D1E1F202102030405060708090A0B0C0D0E0F101112131415161718191A1B1C1D1E1F202'","Line has odd-length data, truncating: '#05306:02030405060708090A0B0C0D0E0F101112131415161718191A1B1C1D1E1F202102030405060708090A0B0C0D0E0F101112131415161718191A1B1C1D1E1F202'","Line has odd-length data, truncating: '#05406:02030405060708090A0B0C0D0E0F101112131415161718191A1B1C1D1E1F202102030405060708090A0B0C0D0E0F101112131415161718191A1B1C1D1E1F202'","Line has odd-length data, truncating: '#05506:02030405060708090A0B0C0D0E0F101112131415161718191A1B1C1D1E1F202102030405060708090A0B0C0D0E0F101112131415161718191A1B1C1D1E1F202'","Line has odd-length data, truncating: '#05606:02030405060708090A0B0C0D0E0F101112131415161718191A1B1C1D1E1F202102030405060708090A0B0C0D0E0F101112131415161718191A1B1C1D1E1F202'","Line has odd-length data, truncating: '#05706:02030405060708090A0B0C0D0E0F101112131415161718191A1B1C1D1E1F202102030405060708090A0B0C0D0E0F101112131415161718191A1B1C1D1E1F202'","Line has odd-length data, truncating: '#05806:02030405060708090A0B0C0D0E0F101112131415161718191A1B1C1D1E1F202102030405060708090A0B0C0D0E0F101112131415161718191A1B1C1D1E1F202'","Line has odd-length data, truncating: '#05906:02030405060708090A0B0C0D0E0F101112131415161718191A1B1C1D1E1F202102030405060708090A0B0C0D0E0F101112131415161718191A1B1C1D1E1F202'","Line has odd-length data, truncating: '#06006:02030405060708090A0B0C0D0E0F101112131415161718191A1B1C1D1E1F202102030405060708090A0B0C0D0E0F101112131415161718191A1B1C1D1E1F202'","Line has odd-length data, truncating: '#06106:02030405060708090A0B0C0D0E0F101112131415161718191A1B1C1D1E1F202102030405060708090A0B0C0D0E0F101112131415161718191A1B1C1D1E1F202'","Line has odd-length data, truncating: '#06206:02030405060708090A0B0C0D0E0F101112131415161718191A1B1C1D1E1F202102030405060708090A0B0C0D0E0F101112131415161718191A1B1C1D1E1F202'","Line has odd-length data, truncating: '#06306:02030405060708090A0B0C0D0E0F101112131415161718191A1B1C1D1E1F202102030405060708090A0B0C0D0E0F101112131415161718191A1B1C1D1E1F202'","Line has odd-length data, truncating: '#06406:02030405060708090A0B0C0D0E0F101112131415161718191A1B1C1D1E1F202102030405060708090A0B0C0D0E0F101112131415161718191A1B1C1D1E1F202'","Line has odd-length data, truncating: '#06506:02030405060708090A0B0C0D0E0F101112131415161718191A1B1C1D1E1F202102030405060708090A0B0C0D0E0F101112131415161718191A1B1C1D1E1F202'","Line has odd-length data, truncating: '#06606:02030405060708090A0B0C0D0E0F101112131415161718191A1B1C1D1E1F202102030405060708090A0B0C0D0E0F101112131415161718191A1B1C1D1E1F202'","Line has odd-length data, truncating: '#06706:02030405060708090A0B0C0D0E0F101112131415161718191A1B1C1D1E1F202102030405060708090A0B0C0D0E0F101112131415161718191A1B1C1D1E1F202'","Line has odd-length data, truncating: '#06806:02030405060708090A0B0C0D0E0F101112131415161718191A1B1C1D1E1F202102030405060708090A0B0C0D0E0F101112131415161718191A1B1C1D1E1F202'","Line has odd-length data, truncating: '#06906:02030405060708090A0B0C0D0E0F101112131415161718191A1B1C1D1E1F202102030405060708090A0B0C0D0E0F101112131415161718191A1B1C1D1E1F202'","Line has odd-length data, truncating: '#07006:02030405060708090A0B0C0D0E0F101112131415161718191A1B1C1D1E1F202102030405060708090A0B0C0D0E0F101112131415161718191A1B1C1D1E1F202'","Line has odd-length data, truncating: '#07106:02030405060708090A0B0C0D0E0F101112131415161718191A1B1C1D1E1F202102030405060708090A0B0C0D0E0F101112131415161718191A1B1C1D1E1F202'","Line has odd-length data, truncating: '#07206:02030405060708090A0B0C0D0E0F101112131415161718191A1B1C1D1E1F202102030405060708090A0B0C0D0E0F101112131415161718191A1B1C1D1E1F202'","Line has odd-length data, truncating: '#07306:02030405060708090A0B0C0D0E0F101112131415161718191A1B1C1D1E1F202102030405060708090A0B0C0D0E0F101112131415161718191A1B1C1D1E1F202'","Line has odd-length data, truncating: '#07406:02030405060708090A0B0C0D0E0F101112131415161718191A1B1C1D1E1F202102030405060708090A0B0C0D0E0F101112131415161718191A1B1C1D1E1F202'","Line has odd-length data, truncating: '#07506:02030405060708090A0B0C0D0E0F101112131415161718191A1B1C1D1E1F202102030405060708090A0B0C0D0E0F101112131415161718191A1B1C1D1E1F202'","Line has odd-length data, truncating: '#07606:02030405060708090A0B0C0D0E0F101112131415161718191A1B1C1D1E1F202102030405060708090A0B0C0D0E0F101112131415161718191A1B1C1D1E1F202'","Line has odd-length data, truncating: '#07706:02030405060708090A0B0C0D0E0F101112131415161718191A1B1C1D1E1F202102030405060708090A0B0C0D0E0F101112131415161718191A1B1C1D1E1F202'","Line has odd-length data, truncating: '#07806:02030405060708090A0B0C0D0E0F101112131415161718191A1B1C1D1E1F202102030405060708090A0B0C0D0E0F101112131415161718191A1B1C1D1E1F202'","Line has odd-length data, truncating: '#07906:02030405060708090A0B0C0D0E0F101112131415161718191A1B1C1D1E1F202102030405060708090A0B0C0D0E0F101112131415161718191A1B1C1D1E1F202'","Line has odd-length data, truncating: '#08006:02030405060708090A0B0C0D0E0F101112131415161718191A1B1C1D1E1F202102030405060708090A0B0C0D0E0F101112131415161718191A1B1C1D1E1F202'","Line has odd-length data, truncating: '#08106:02030405060708090A0B0C0D0E0F101112131415161718191A1B1C1D1E1F202102030405060708090A0B0C0D0E0F101112131415161718191A1B1C1D1E1F202'","Line has odd-length data, truncating: '#08206:02030405060708090A0B0C0D0E0F101112131415161718191A1B1C1D1E1F202102030405060708090A0B0C0D0E0F101112131415161718191A1B1C1D1E1F202'","Line has odd-length data, truncating: '#08306:02030405060708090A0B0C0D0E0F101112131415161718191A1B1C1D1E1F202102030405060708090A0B0C0D0E0F101112131415161718191A1B1C1D1E1F202'","Line has odd-length data, truncating: '#08406:02030405060708090A0B0C0D0E0F101112131415161718191A1B1C1D1E1F202102030405060708090A0B0C0D0E0F101112131415161718191A1B1C1D1E1F202'","Line has odd-length data, truncating: '#08506:02030405060708090A0B0C0D0E0F101112131415161718191A1B1C1D1E1F202102030405060708090A0B0C0D0E0F101112131415161718191A1B1C1D1E1F202'","Line has odd-length data, truncating: '#08606:02030405060708090A0B0C0D0E0F101112131415161718191A1B1C1D1E1F202102030405060708090A0B0C0D0E0F101112131415161718191A1B1C1D1E1F202'","Line has odd-length data, truncating: '#08706:02030405060708090A0B0C0D0E0F101112131415161718191A1B1C1D1E1F202102030405060708090A0B0C0D0E0F101112131415161718191A1B1C1D1E1F202'","Line has odd-length data, truncating: '#08806:02030405060708090A0B0C0D0E0F101112131415161718191A1B1C1D1E1F202102030405060708090A0B0C0D0E0F101112131415161718191A1B1C1D1E1F202'","Line has odd-length data, truncating: '#08906:02030405060708090A0B0C0D0E0F101112131415161718191A1B1C1D1E1F202102030405060708090A0B0C0D0E0F101112131415161718191A1B1C1D1E1F202'","Line has odd-length data, truncating: '#09006:02030405060708090A0B0C0D0E0F101112131415161718191A1B1C1D1E1F202102030405060708090A0B0C0D0E0F101112131415161718191A1B1C1D1E1F202'","Line has odd-length data, truncating: '#09106:02030405060708090A0B0C0D0E0F101112131415161718191A1B1C1D1E1F202102030405060708090A0B0C0D0E0F101112131415161718191A1B1C1D1E1F202'","Line has odd-length data, truncating: '#09206:02030405060708090A0B0C0D0E0F101112131415161718191A1B1C1D1E1F202102030405060708090A0B0C0D0E0F101112131415161718191A1B1C1D1E1F202'","Line has odd-length data, truncating: '#09306:02030405060708090A0B0C0D0E0F101112131415161718191A1B1C1D1E1F202102030405060708090A0B0C0D0E0F101112131415161718191A1B1C1D1E1F202'","Line has odd-length data, truncating: '#09406:02030405060708090A0B0C0D0E0F101112131415161718191A1B1C1D1E1F202102030405060708090A0B0C0D0E0F101112131415161718191A1B1C1D1E1F202'","Line has odd-length data, truncating: '#09506:02030405060708090A0B0C0D0E0F101112131415161718191A1B1C1D1E1F202102030405060708090A0B0C0D0E0F101112131415161718191A1B1C1D1E1F202'","Line has odd-length data, truncating: '#09606:02030405060708090A0B0C0D0E0F101112131415161718191A1B1C1D1E1F202102030405060708090A0B0C0D0E0F101112131415161718191A1B1C1D1E1F202'","Line has odd-length data, truncating: '#09706:02030405060708090A0B0C0D0E0F101112131415161718191A1B1C1D1E1F202102030405060708090A0B0C0D0E0F101112131415161718191A1B1C1D1E1F202'","Line has odd-length data, truncating: '#09806:02030405060708090A0B0C0D0E0F101112131415161718191A1B1C1D1E1F202102030405060708090A0B0C0D0E0F101112131415161718191A1B1C1D1E1F202'","Line has odd-length data, truncating: '#09906:02030405060708090A0B0C0D0E0F101112131415161718191A1B1C1D1E1F202102030405060708090A0B0C0D0E0F101112131415161718191A1B1C1D1E1F202'","Line has odd-length data, truncating: '#10006:02030405060708090A0B0C0D0E0F101112131415161718191A1B1C1D1E1F202102030405060708090A0B0C0D0E0F101112131415161718191A1B1C1D1E1F202'","Line has odd-length data, truncating: '#10106:02030405060708090A0B0C0D0E0F101112131415161718191A1B1C1D1E1F202102030405060708090A0B0C0D0E0F101112131415161718191A1B1C1D1E1F202'","Line has odd-length data, truncating: '#10206:02030405060708090A0B0C0D0E0F101112131415161718191A1B1C1D1E1F202102030405060708090A0B0C0D0E0F101112131415161718191A1B1C1D1E1F202'","Line has odd-length data, truncating: '#10306:02030405060708090A0B0C0D0E0F101112131415161718191A1B1C1D1E1F202102030405060708090A0B0C0D0E0F101112131415161718191A1B1C1D1E1F202'","Line has odd-length data, truncating: '#10406:02030405060708090A0B0C0D0E0F101112131415161718191A1B1C1D1E1F202102030405060708090A0B0C0D0E0F101112131415161718191A1B1C1D1E1F202'","Line has odd-length data, truncating: '#10506:02030405060708090A0B0C0D0E0F101112131415161718191A1B1C1D1E1F202102030405060708090A0B0C0D0E0F101112131415161718191A1B1C1D1E1F202'","Line has odd-length data, truncating: '#10606:02030405060708090A0B0C0D0E0F101112131415161718191A1B1C1D1E1F202102030405060708090A0B0C0D0E0F101112131415161718191A1B1C1D1E1F202'","Line has odd-length data, truncating: '#10706:02030405060708090A0B0C0D0E0F101112131415161718191A1B1C1D1E1F202102030405060708090A0B0C0D0E0F101112131415161718191A1B1C1D1E1F202'","Line has odd-length data, truncating: '#10806:02030405060708090A0B0C0D0E0F101112131415161718191A1B1C1D1E1F202102030405060708090A0B0C0D0E0F101112131415161718191A1B1C1D1E1F202'","Line has odd-length data, truncating: '#10906:02030405060708090A0B0C0D0E0F101112131415161718191A1B1C1D1E1F202102030405060708090A0B0C0D0E0F101112131415161718191A1B1C1D1E1F202'","Line has odd-length data, truncating: '#11006:02030405060708090A0B0C0D0E0F101112131415161718191A1B1C1D1E1F202102030405060708090A0B0C0D0E0F101112131415161718191A1B1C1D1E1F202'","Line has odd-length data, truncating: '#11106:02030405060708090A0B0C0D0E0F101112131415161718191A1B1C1D1E1F202102030405060708090A0B0C0D0E0F101112131415161718191A1B1C1D1E1F202'","Line has odd-length data, truncating: '#11206:02030405060708090A0B0C0D0E0F101112131415161718191A1B1C1D1E1F202102030405060708090A0B0C0D0E0F101112131415161718191A1B1C1D1E1F202'","Line has odd-length data, truncating: '#11306:02030405060708090A0B0C0D0E0F101112131415161718191A1B1C1D1E1F202102030405060708090A0B0C0D0E0F101112131415161718191A1B1C1D1E1F202'","Line has odd-length data, truncating: '#11406:02030405060708090A0B0C0D0E0F101112131415161718191A1B1C1D1E1F202102030405060708090A0B0C0D0E0F101112131415161718191A1B1C1D1E1F202'","Line has odd-length data, truncating: '#11506:02030405060708090A0B0C0D0E0F101112131415161718191A1B1C1D1E1F202102030405060708090A0B0C0D0E0F101112131415161718191A1B1C1D1E1F202'","Line has odd-length data, truncating: '#11606:02030405060708090A0B0C0D0E0F101112131415161718191A1B1C1D1E1F202102030405060708090A0B0C0D0E0F101112131415161718191A1B1C1D1E1F202'","Line has odd-length data, truncating: '#11706:02030405060708090A0B0C0D0E0F101112131415161718191A1B1C1D1E1F202102030405060708090A0B0C0D0E0F101112131415161718191A1B1C1D1E1F202'","Line has odd-length data, truncating: '#11806:02030405060708090A0B0C0D0E0F101112131415161718191A1B1C1D1E1F202102030405060708090A0B0C0D0E0F101112131415161718191A1B1C1D1E1F202'","Line has odd-length data, truncating: '#11906:02030405060708090A0B0C0D0E0F101112131415161718191A1B1C1D1E1F202102030405060708090A0B0C0D0E0F101112131415161718191A1B1C1D1E1F202'","Line has odd-length data, truncating: '#12006:02030405060708090A0B0C0D0E0F101112131415161718191A1B1C1D1E1F202102030405060708090A0B0C0D0E0F101112131415161718191A1B1C1D1E1F202'","Line has odd-length data, truncating: '#12106:02030405060708090A0B0C0D0E0F101112131415161718191A1B1C1D1E1F202102030405060708090A0B0C0D0E0F101112131415161718191A1B1C1D1E1F202'","Line has odd-length data, truncating: '#12206:02030405060708090A0B0C0D0E0F101112131415161718191A1B1C1D1E1F202102030405060708090A0B0C0D0E0F101112131415161718191A1B1C1D1E1F202'","Line has odd-length data, truncating: '#12306:02030405060708090A0B0C0D0E0F101112131415161718191A1B1C1D1E1F202102030405060708090A0B0C0D0E0F101112131415161718191A1B1C1D1E1F202'","Line has odd-length data, truncating: '#12406:02030405060708090A0B0C0D0E0F101112131415161718191A1B1C1D1E1F202102030405060708090A0B0C0D0E0F101112131415161718191A1B1C1D1E1F202'","Line has odd-length data, truncating: '#12506:02030405060708090A0B0C0D0E0F101112131415161718191A1B1C1D1E1F202102030405060708090A0B0C0D0E0F101112131415161718191A1B1C1D1E1F202'","Line has odd-length data, truncating: '#12606:02030405060708090A0B0C0D0E0F101112131415161718191A1B1C1D1E1F202102030405060708090A0B0C0D0E0F101112131415161718191A1B1C1D1E1F202'","Line has odd-length data, truncating: '#12706:02030405060708090A0B0C0D0E0F101112131415161718191A1B1C1D1E1F202102030405060708090A0B0C0D0E0F101112131415161718191A1B1C1D1E1F202'","Line has odd-length data, truncating: '#12806:02030405060708090A0B0C0D0E0F101112131415161718191A1B1C1D1E1F202102030405060708090A0B0C0D0E0F101112131415161718191A1B1C1D1E1F202'","Line has odd-length data, truncating: '#12906:02030405060708090A0B0C0D0E0F101112131415161718191A1B1C1D1E1F202102030405060708090A0B0C0D0E0F101112131415161718191A1B1C1D1E1F202'","Line has odd-length data, truncating: '#13006:02030405060708090A0B0C0D0E0F101112131415161718191A1B1C1D1E1F202102030405060708090A0B0C0D0E0F101112131415161718191A1B1C1D1E1F202'","Line has odd-length data, truncating: '#13106:02030405060708090A0B0C0D0E0F101112131415161718191A1B1C1D1E1F202102030405060708090A0B0C0D0E0F101112131415161718191A1B1C1D1E1F202'","Line has odd-length data, truncating: '#13206:02030405060708090A0B0C0D0E0F101112131415161718191A1B1C1D1E1F202102030405060708090A0B0C0D0E0F101112131415161718191A1B1C1D1E1F202'","Line has odd-length data, truncating: '#13306:02030405060708090A0B0C0D0E0F101112131415161718191A1B1C1D1E1F202102030405060708090A0B0C0D0E0F101112131415161718191A1B1C1D1E1F202'","Line has odd-length data, truncating: '#13406:02030405060708090A0B0C0D0E0F101112131415161718191A1B1C1D1E1F202102030405060708090A0B0C0D0E0F101112131415161718191A1B1C1D1E1F202'","Line has odd-length data, truncating: '#13506:02030405060708090A0B0C0D0E0F101112131415161718191A1B1C1D1E1F202102030405060708090A0B0C0D0E0F101112131415161718191A1B1C1D1E1F202'","Line has odd-length data, truncating: '#13606:02030405060708090A0B0C0D0E0F101112131415161718191A1B1C1D1E1F202102030405060708090A0B0C0D0E0F101112131415161718191A1B1C1D1E1F202'","Line has odd-length data, truncating: '#13706:02030405060708090A0B0C0D0E0F101112131415161718191A1B1C1D1E1F202102030405060708090A0B0C0D0E0F101112131415161718191A1B1C1D1E1F202'","Line has odd-length data, truncating: '#13806:02030405060708090A0B0C0D0E0F101112131415161718191A1B1C1D1E1F202102030405060708090A0B0C0D0E0F101112131415161718191A1B1C1D1E1F202'","Line has odd-length data, truncating: '#13906:02030405060708090A0B0C0D0E0F101112131415161718191A1B1C1D1E1F202102030405060708090A0B0C0D0E0F101112131415161718191A1B1C1D1E1F202'","Line has odd-length data, truncating: '#14006:02030405060708090A0B0C0D0E0F101112131415161718191A1B1C1D1E1F202102030405060708090A0B0C0D0E0F101112131415161718191A1B1C1D1E1F202'","Line has odd-length data, truncating: '#14106:02030405060708090A0B0C0D0E0F101112131415161718191A1B1C1D1E1F202102030405060708090A0B0C0D0E0F101112131415161718191A1B1C1D1E1F202'","Line has odd-length data, truncating: '#14206:02030405060708090A0B0C0D0E0F101112131415161718191A1B1C1D1E1F202102030405060708090A0B0C0D0E0F101112131415161718191A1B1C1D1E1F202'","Line has odd-length data, truncating: '#14306:02030405060708090A0B0C0D0E0F101112131415161718191A1B1C1D1E1F202102030405060708090A0B0C0D0E0F101112131415161718191A1B1C1D1E1F202'","Line has odd-length data, truncating: '#14406:02030405060708090A0B0C0D0E0F101112131415161718191A1B1C1D1E1F202102030405060708090A0B0C0D0E0F101112131415161718191A1B1C1D1E1F202'","Line has odd-length data, truncating: '#14506:02030405060708090A0B0C0D0E0F101112131415161718191A1B1C1D1E1F202102030405060708090A0B0C0D0E0F101112131415161718191A1B1C1D1E1F202'","Line has odd-length data, truncating: '#14606:02030405060708090A0B0C0D0E0F101112131415161718191A1B1C1D1E1F202102030405060708090A0B0C0D0E0F101112131415161718191A1B1C1D1E1F202'","Line has odd-length data, truncating: '#14706:02030405060708090A0B0C0D0E0F101112131415161718191A1B1C1D1E1F202102030405060708090A0B0C0D0E0F101112131415161718191A1B1C1D1E1F202'","Line has odd-length data, truncating: '#14806:02030405060708090A0B0C0D0E0F101112131415161718191A1B1C1D1E1F202102030405060708090A0B0C0D0E0F101112131415161718191A1B1C1D1E1F202'","Line has odd-length data, truncating: '#14906:02030405060708090A0B0C0D0E0F101112131415161718191A1B1C1D1E1F202102030405060708090A0B0C0D0E0F101112131415161718191A1B1C1D1E1F202'","Line has odd-length data, truncating: '#15006:02030405060708090A0B0C0D0E0F101112131415161718191A1B1C1D1E1F202102030405060708090A0B0C0D0E0F101112131415161718191A1B1C1D1E1F202'"],"axis_intensities":{"chord":"green","stream":"green","peak":"green","scratch":"red","soft":"red","ln":"yellow","stair":"green","distraction":"green"},"tags":["advanced_ln","extreme_burst"],"scales":[]}