{"md5":"a9f20d9357bac2ac9a5a3845a169d352","headers":{"title":"Alastor [MANIAC7]","artist":"鳩 / obj:A-zert","genre":"DarkBreaks","playlevel":"15","base_bpm":170.0},"mode":"SP","scope":"playable_only","scaling_mode":"p99_linear","params":{"stream_window_ticks":48,"stream_density_threshold_per_beat":4.0,"peak_window_ticks":192,"peak_min_window_notes":4,"peak_min_window_sec":0.05,"felt_bpm_trigger_eff_bpm":500.0,"felt_bpm_trigger_peak_per_sec":200.0,"felt_bpm_target_peak_per_sec":100.0,"felt_bpm_floor":30.0,"jack_window_ticks":24,"soft_burst_ref":8.0,"soft_freq_ref":0.1,"soft_burst_exp":1.5,"soft_freq_exp":1.5,"chord_time_threshold_ms":16.67,"sp_distraction_min_scratches":3,"sp_distraction_bin_sec":0.25,"sp_distraction_t_key":2,"sp_distraction_gap_bins":2,"dp_distraction_window_sec_min":0.2,"dp_distraction_window_sec_max":0.8,"stream_density_ref_per_sec":40.0,"peak_density_ref_per_sec":70.0,"chord_size_ref":3.5,"ln_simultaneity_ref":0.05,"scratch_density_ref_per_sec":1.5,"scratch_ratio_ref":0.1,"distraction_density_ref":2.0,"distraction_event_ref":0.15},"raw_axes":{"chord":1.6519795657726692,"stream":19.071147722838397,"scratch_per_sec":0.6477631871800579,"scratch_burst_max_per_sec":3.0,"scratch_max_run_sec":10.941176470588232,"soft":0.011972837180091065,"stair":0.16634676903390916,"peak":25.5,"ln_m1_short_rate_rt":0.0,"ln_m2_density_rt":0.0,"ln_m2_burst_max_rt":0.0,"ln_m3_density_rt":0.0,"ln_m_concurrent_rt":0.0,"adv_hand_imb":0.0,"adv_rel_pressure_1beat":0.0,"adv_ln_hold_min_beats":0.0,"adv_ln_chord_big_rate":0.0,"adv_ln_scatter_cv":0.0,"distraction":2.9966614734030714},"x_chord":0.424,"x_stream":0.492,"x_scratch":0.139,"x_soft":0.036,"x_ln":0.0,"x_stair":0.471,"x_peak":0.428,"x_distraction":0.184,"ln_advanced_score":0.0,"submetrics":{"chord":{"chord_rate":0.7062579821200511,"avg_chord_size":2.3390596745027126,"chord_positions":1106,"total_positions":1566},"stream":{"stream_coverage":0.9982993197278912,"stream_density_mean":6.892962743938498,"stream_density_mean_per_sec":19.103636901241867,"stream_windows":6,"notes_in_stream":2935,"total_notes":2940,"intervals":[[192,13284],[13320,13476],[13500,13668],[13704,13860],[13920,13968],[13980,20952]]},"scratch":{"scratch_ratio":0.035116508040695764,"scratch_positions_ratio":0.06832694763729247,"scratch_with_key_chord_rate":0.9813084112149533,"scratch_per_sec":0.6477631871800579,"scratch_burst_max_per_sec":3.0,"scratch_burst_window_sec":1.0,"scratch_max_run_sec":10.941176470588232,"ls_count":0,"ls_per_sec":0.0,"ls_complexity_mean":0.0,"scratch_notes":107,"scratch_positions":107,"total_notes":3047,"total_positions":1566,"chart_seconds":165.18382352941177},"soft":{"base_bpm":170.0,"intensity":0.02477847062684608,"up_intensity":0.0,"down_intensity":0.02477847062684608,"max_intensity":0.5,"max_up_intensity":0.0,"max_down_intensity":0.5,"step_frequency":0.01818181818181818,"ramp_frequency":0.01818181818181818,"continuity_beats":32.0,"off_base_note_ratio":0.04955694125369216,"gimmick_burst_score":0.6585060449050086,"max_off_base_density_per_beat":4.71875,"base_mean_density_per_beat":7.165841584158416,"base_density_source":"on_base","distinct_off_base_bpm_count":1,"bpm_change_events":2,"measure_count":110},"ln":{"ln_ratio":0.0,"ln_hold_time_mean_beats":0.0,"ln_simultaneity_rate":0.0,"ln_simultaneity_weighted":0.0,"ln_count":0,"ln_count_raw":0,"ln_positions":0,"total_notes":3047,"m1_short_count_rt":0,"m1_short_rate_rt":0.0,"m2_long_count_rt":0,"m2_density_rt":0.0,"m2_burst_max_rt":0.0,"m3_density_rt":0.0,"m_concurrent_rt":0.0,"total_long_sec":0.0,"long_active_sec":0.0,"long_hold_sec_mean":0.0,"long_hold_sec_max":0.0,"adv_hand_imb":0.0,"adv_rel_pressure_1beat":0.0,"adv_ln_hold_min_beats":0.0,"adv_ln_chord_big_rate":0.0,"adv_ln_scatter_cv":0.0},"stair":{"stair_index":0.16634676903390916,"stair_transitions":260,"eligible_transitions":1563},"peak":{"peak_local_max_density":9.0,"peak_local_max_density_per_sec":25.5,"peak_max_chord_size":5,"peak_concentration":0.4034013605442177,"total_notes":2940,"intervals":[[5532,6960],[10176,13260],[16488,16836],[17256,17604],[18984,20628],[20736,20928]]},"jack":{"jack_pairs":9,"jack_in_stream_pairs":9,"jack_outside_pairs":0,"pure_jack_per_sec":0.0,"flow_break_per_stream_sec":0.05579614350184619,"stream_seconds":161.3014705882353,"non_stream_seconds":3.882352941176464,"chart_seconds":165.18382352941177,"window_ticks":24,"min_region_sec":10.0},"distraction":{"mode_formulation":"SP","v3_score":2.9966614734030714,"qualifying_intervals":2,"qualifying_flow_sec":143.25,"qualifying_scratches":106,"scratch_chord_pair_count":72,"chord_time_threshold_sec":0.01667,"min_scratches":3,"bin_sec":0.25,"t_key":2,"gap_bins":2}},"warnings":[],"axis_intensities":{"chord":"yellow","stream":"yellow","peak":"green","scratch":"yellow","soft":"yellow","ln":null,"stair":"yellow","distraction":"yellow"},"tags":[],"scales":["★"]}