{"md5":"d3741abadd924dd834aa596c420a3ce8","headers":{"title":"Holy Wind[ULTIMATE]","artist":"69 de 74","genre":"RENAISSANCE","playlevel":"175","base_bpm":179.0},"mode":"SP","scope":"playable_only","scaling_mode":"p99_linear","params":{"stream_window_ticks":48,"stream_density_threshold_per_beat":4.0,"peak_window_ticks":192,"peak_min_window_notes":4,"peak_min_window_sec":0.05,"felt_bpm_trigger_eff_bpm":500.0,"felt_bpm_trigger_peak_per_sec":200.0,"felt_bpm_target_peak_per_sec":100.0,"felt_bpm_floor":30.0,"jack_window_ticks":24,"soft_burst_ref":8.0,"soft_freq_ref":0.1,"soft_burst_exp":1.5,"soft_freq_exp":1.5,"chord_time_threshold_ms":16.67,"sp_distraction_min_scratches":3,"dp_distraction_window_sec_min":0.2,"dp_distraction_window_sec_max":0.8,"stream_density_ref_per_sec":40.0,"peak_density_ref_per_sec":70.0,"chord_size_ref":3.5,"ln_simultaneity_ref":0.05,"scratch_density_ref_per_sec":1.5,"scratch_ratio_ref":0.1,"distraction_density_ref":2.0,"distraction_event_ref":0.15},"raw_axes":{"chord":1.4283105022831049,"stream":19.380378546700765,"scratch":0.08918552239253778,"soft":0.0,"ln":0.032409581963363084,"stair":0.1773308957952468,"peak":29.087500000000002,"distraction":0.8890657022302593},"x_chord":0.36,"x_stream":0.483,"x_scratch":0.213,"x_soft":0.0,"x_ln":0.513,"x_stair":0.523,"x_peak":0.469,"x_distraction":0.235,"submetrics":{"chord":{"chord_rate":0.4840182648401826,"avg_chord_size":2.950943396226415,"chord_positions":530,"total_positions":1095},"stream":{"stream_coverage":0.9826209488022546,"stream_density_mean":6.611111111111111,"stream_density_mean_per_sec":19.723148148148148,"stream_windows":10,"notes_in_stream":2092,"total_notes":2129,"intervals":[[348,6576],[6636,6960],[7020,7152],[7164,7344],[7452,7728],[7836,7920],[7956,8112],[8172,8496],[8556,8688],[8700,16344]]},"scratch":{"scratch_ratio":0.06904650070455613,"scratch_positions_ratio":0.13424657534246576,"scratch_with_key_chord_rate":0.9931972789115646,"scratch_per_sec":1.2916733141068908,"scratch_burst_max_per_sec":5.0,"scratch_burst_window_sec":1.0,"scratch_notes":147,"scratch_positions":147,"total_notes":2129,"total_positions":1095,"chart_seconds":113.80586592178771},"soft":{"base_bpm":179.0,"intensity":0.0,"up_intensity":0.0,"down_intensity":0.0,"max_intensity":0.0,"max_up_intensity":0.0,"max_down_intensity":0.0,"step_frequency":0.0,"ramp_frequency":0.0,"continuity_beats":0.0,"off_base_note_ratio":0.0,"gimmick_burst_score":0.0,"max_off_base_density_per_beat":0.0,"base_mean_density_per_beat":6.256259204712813,"base_density_source":"on_base","distinct_off_base_bpm_count":0,"bpm_change_events":0,"measure_count":85},"ln":{"ln_ratio":0.020666979802724285,"ln_hold_time_mean_beats":1.0909090909090908,"ln_simultaneity_rate":0.032409581963363084,"ln_simultaneity_weighted":0.032409581963363084,"ln_count":44,"ln_positions":40,"total_notes":2129},"stair":{"stair_index":0.1773308957952468,"stair_transitions":194,"eligible_transitions":1094},"peak":{"peak_local_max_density":9.75,"peak_local_max_density_per_sec":29.087500000000002,"peak_max_chord_size":6,"peak_concentration":0.38750587130108033,"total_notes":2129,"intervals":[[1764,1968],[3264,3504],[6132,6576],[9324,9768],[9804,10080],[10188,10464],[10572,10848],[10932,11304],[11340,11616],[11736,12000],[12120,12780],[13836,14232],[15108,15924],[16092,16296]]},"jack":{"jack_pairs":0,"jack_in_stream_pairs":0,"jack_outside_pairs":0,"pure_jack_per_sec":0.0,"flow_break_per_stream_sec":0.0,"stream_seconds":107.77234636871509,"non_stream_seconds":6.033519553072622,"chart_seconds":113.80586592178771,"window_ticks":24,"min_region_sec":10.0},"distraction":{"mode_formulation":"SP","qualifying_window_count":2,"qualifying_scratches":145,"qualifying_flow_sec":96.54329608938548,"distract_density":1.5019168173598554,"distract_event_per_sec":0.020716094032549728,"scratch_chord_pair_count":217,"chord_time_threshold_sec":0.01667,"min_scratches":3}},"warnings":["Unterminated LNOBJ LN on lane P1_SCR started at m84 pos0.875; closing at EOF","Unterminated LNOBJ LN on lane P1_KEY1 started at m84 pos0.875; closing at EOF","Unterminated LNOBJ LN on lane P1_KEY5 started at m84 pos0.875; closing at EOF","Unterminated LNOBJ LN on lane P1_KEY2 started at m84 pos0.625; closing at EOF","Unterminated LNOBJ LN on lane P1_KEY3 started at m84 pos0.875; closing at EOF","Unterminated LNOBJ LN on lane P1_KEY6 started at m84 pos0.6875; closing at EOF","Unterminated LNOBJ LN on lane P1_KEY7 started at m84 pos0.875; closing at EOF","Unterminated LNOBJ LN on lane P1_KEY4 started at m84 pos0.75; closing at EOF"],"tags":["scratch_active","ln_chart"],"scales":["sl"]}