{"md5":"f18af3f9497cc3fa9844f59392a261fe","headers":{"title":"Shape [Polygon]","artist":"Ploutonendou","genre":"TRANCE","playlevel":"24","base_bpm":143.0},"mode":"SP","scope":"playable_only","scaling_mode":"reference","params":{"stream_window_ticks":48,"stream_density_threshold_per_beat":4.0,"peak_window_ticks":192,"jack_window_ticks":24,"soft_burst_ref":8.0,"soft_freq_ref":0.1,"soft_burst_exp":1.5,"soft_freq_exp":1.5,"stream_density_ref_per_sec":40.0,"peak_density_ref_per_sec":70.0,"chord_size_ref":3.5,"ln_simultaneity_ref":0.05},"x_chord":0.7083125933300148,"x_stream":0.648908299899422,"x_scratch":0.006331117442228553,"x_soft":0.0,"x_ln":0.0,"x_stair":0.14036617262423715,"x_peak":0.6894642857142858,"x_jack":0.006102877070619006,"submetrics":{"chord":{"chord_rate":0.7273519163763066,"avg_chord_size":3.408383233532934,"chord_positions":835,"total_positions":1148},"stream":{"stream_coverage":0.9873377651155429,"stream_density_mean":11.030438675022381,"stream_density_mean_per_sec":26.28921217547001,"stream_windows":18,"notes_in_stream":3119,"total_notes":3159},"scratch":{"scratch_ratio":0.006331117442228553,"scratch_positions_ratio":0.017421602787456445,"scratch_with_key_chord_rate":1.0,"scratch_notes":20,"scratch_positions":20,"total_notes":3159,"total_positions":1148},"soft":{"base_bpm":143.0,"intensity":0.0,"up_intensity":0.0,"down_intensity":0.0,"max_intensity":0.0,"max_up_intensity":0.0,"max_down_intensity":0.0,"step_frequency":0.0,"ramp_frequency":0.0,"continuity_beats":0.0,"off_base_note_ratio":0.0,"gimmick_burst_score":0.0,"max_off_base_density_per_beat":0.0,"base_mean_density_per_beat":9.509036144578314,"base_density_source":"on_base","distinct_off_base_bpm_count":0,"bpm_change_events":0,"measure_count":84},"ln":{"ln_ratio":0.0,"ln_hold_time_mean_beats":0.0,"ln_simultaneity_rate":0.0,"ln_simultaneity_weighted":0.0,"ln_count":0,"ln_positions":0,"total_notes":3159},"stair":{"stair_index":0.14036617262423715,"stair_transitions":161,"eligible_transitions":1147},"peak":{"peak_local_max_density":20.25,"peak_local_max_density_per_sec":48.2625,"peak_max_chord_size":7,"peak_concentration":0.33238366571699907,"total_notes":3159},"jack":{"jack_ratio":0.006102877070619006,"jack_transitions":7,"all_transitions":1147}},"warnings":[],"tags":["chord_heavy","dense_chart"],"scales":["st"]}